CHANGES.txt
CONTRIBUTORS.txt
MANIFEST.in
README.rst
setup.py
Products/__init__.py
Products.jsonserver.egg-info/PKG-INFO
Products.jsonserver.egg-info/SOURCES.txt
Products.jsonserver.egg-info/dependency_links.txt
Products.jsonserver.egg-info/entry_points.txt
Products.jsonserver.egg-info/namespace_packages.txt
Products.jsonserver.egg-info/not-zip-safe
Products.jsonserver.egg-info/requires.txt
Products.jsonserver.egg-info/top_level.txt
Products/jsonserver/__init__.py
Products/jsonserver/interfaces.py
Products/jsonserver/jsonrpc.py
Products/jsonserver/meta.zcml
Products/jsonserver/metaconfigure.py
Products/jsonserver/tests/__init__.py
Products/jsonserver/tests/test_json.py
Products/jsonserver/tests/test_publisher.py