Metadata-Version: 1.1
Name: Products.jsonserver
Version: 1.2b6
Summary: A JSON-RPC server for Zope2
Home-page: http://pypi.python.org/pypi/Products.jsonserver/
Author: Tom Gross
Author-email: itconsense@gmail.com
License: GPL
Keywords: json json-rpc
Platform: UNKNOWN
Classifier: Framework :: Zope2
Classifier: Framework :: Plone
Classifier: Programming Language :: Python
